conversallink/__init__.py
conversallink/__main__.py
conversallink/cli.py
conversallink/export.py
conversallink/html_export.py
conversallink/recorder.py
conversallink/transcriber.py
conversallink/utils.py
conversallink/templates/transcript_template.html
conversallink-0.4.2.dist-info/METADATA
conversallink-0.4.2.dist-info/WHEEL
conversallink-0.4.2.dist-info/entry_points.txt
conversallink-0.4.2.dist-info/top_level.txt
conversallink-0.4.2.dist-info/RECORD
