Metadata-Version: 2.4
Name: conversallink
Version: 0.4.2
Summary: Lightweight CLI for Recording & Transcribing with Whisper Accuracy
Author: jojihatzz
License: MIT
Classifier: Programming Language :: Python :: 3
Classifier: License :: OSI Approved :: MIT License
Classifier: Operating System :: OS Independent
Requires-Python: >=3.7
Requires-Dist: sounddevice
Requires-Dist: soundfile
Requires-Dist: faster-whisper
Requires-Dist: rich
Requires-Dist: pydub
Dynamic: requires-python
